rox_bridge/__init__.py
rox_bridge/__main__.py
rox_bridge/base.py
rox_bridge/bridge_node.py
rox_bridge/mqtt_leg.py
rox_bridge/py.typed
rox_bridge/utils.py
rox_bridge/version.py
rox_bridge/ws_leg.py
rox_bridge-1.2.1.dist-info/LICENCE
rox_bridge-1.2.1.dist-info/METADATA
rox_bridge-1.2.1.dist-info/WHEEL
rox_bridge-1.2.1.dist-info/top_level.txt
rox_bridge-1.2.1.dist-info/RECORD
