Metadata-Version: 2.1
Name: rox-bridge
Version: 1.2.1
Summary: Bridge mqtt <--> websocket
Author-email: ROX Automation <jev@roxautomation.com>
License: MIT
Project-URL: Homepage, https://gitlab.com/roxautomation/components/mqtt-bridge
Classifier: Development Status :: 3 - Alpha
Classifier: Intended Audience :: Developers
Classifier: Operating System :: OS Independent
Classifier: Programming Language :: Python
Classifier: Programming Language :: Python :: 3.12
Classifier: Topic :: Software Development :: Libraries :: Python Modules
Classifier: Typing :: Typed
Requires-Python: >=3.12
License-File: LICENCE
Requires-Dist: aiomqtt
Requires-Dist: pydantic
Requires-Dist: pydantic-settings
Requires-Dist: click
Requires-Dist: coloredlogs
Requires-Dist: orjson
Requires-Dist: websockets
Provides-Extra: dev
Requires-Dist: build ; extra == 'dev'
Requires-Dist: invoke ; extra == 'dev'
Requires-Dist: ipython ; extra == 'dev'
Requires-Dist: mypy ; extra == 'dev'
Requires-Dist: pre-commit ; extra == 'dev'
Requires-Dist: pytest ; extra == 'dev'
Requires-Dist: pytest-asyncio ; extra == 'dev'
Requires-Dist: pytest-cov ; extra == 'dev'
Requires-Dist: roxbot ; extra == 'dev'
Requires-Dist: ruff ; extra == 'dev'
Requires-Dist: twine ; extra == 'dev'
